generate_summary_of_injuries/__init__.py
generate_summary_of_injuries/_metadata.py
generate_summary_of_injuries/date_extractor.py
generate_summary_of_injuries/diagnosis_extractor.py
generate_summary_of_injuries/icd_code_determiner.py
generate_summary_of_injuries/icd_codes_data.py
generate_summary_of_injuries/main.py
generate_summary_of_injuries/pdf_creator.py
generate_summary_of_injuries/pdf_reader.py
generate_summary_of_injuries/processor.py
generate_summary_of_injuries/data/icd10_codes.csv
tests/__init__.py
tests/test_date_extractor.py
tests/test_dependencies.py
tests/test_diagnosis_extractor.py
tests/test_icd_code_determiner.py
tests/test_pdf_creator.py
tests/test_pdf_reader.py
tests/test_processor.py
injury_summary_generator-1.1.0.dist-info/METADATA
injury_summary_generator-1.1.0.dist-info/WHEEL
injury_summary_generator-1.1.0.dist-info/entry_points.txt
injury_summary_generator-1.1.0.dist-info/top_level.txt
injury_summary_generator-1.1.0.dist-info/RECORD
