Metadata-Version: 2.1
Name: injury-summary-generator
Version: 1.1.0
Summary: A tool to generate summaries of injuries from PDF medical records
Home-page: https://github.com/izgorodin/generate_summary_of_injuries
Author: Eduard Izgorodin
Author-email: edizgorodin@gmail.com
Project-URL: Bug Reports, https://github.com/izgorodin/generate_summary_of_injuries/issues
Project-URL: Source, https://github.com/izgorodin/generate_summary_of_injuries
Keywords: medical,pdf,summary,injury,demand-letter
Classifier: Programming Language :: Python :: 3
Classifier: License :: OSI Approved :: MIT License
Classifier: Operating System :: OS Independent
Requires-Python: >=3.6
Requires-Dist: reportlab
Requires-Dist: spacy
Requires-Dist: nltk
Requires-Dist: python-dateutil
Requires-Dist: pypdf
Requires-Dist: dateparser
Requires-Dist: fuzzywuzzy
